guio/__init__.py
guio/errors.py
guio/event.py
guio/kernel.py
guio/traps.py
guio-0.9.dist-info/LICENSE
guio-0.9.dist-info/METADATA
guio-0.9.dist-info/WHEEL
guio-0.9.dist-info/top_level.txt
guio-0.9.dist-info/RECORD
